archive.py
archive_v1-0.1.2.dist-info/METADATA
archive_v1-0.1.2.dist-info/WHEEL
archive_v1-0.1.2.dist-info/entry_points.txt
archive_v1-0.1.2.dist-info/RECORD
